arducam_config_parser/__init__.py
arducam_config_parser/arducam_config_parser.dll
arducam_config_parser/arducam_config_parser.py
arducam_config_parser-0.1.3.dist-info/METADATA
arducam_config_parser-0.1.3.dist-info/WHEEL
arducam_config_parser-0.1.3.dist-info/top_level.txt
arducam_config_parser-0.1.3.dist-info/RECORD
