Metadata-Version: 2.1
Name: arducam_config_parser
Version: 0.1.3
Summary: arducam_config_parser is a python wrapper for dynamic libraries. 
Home-page: https://github.com/ArduCAM/arducam_config_parser
Author: ArduCam
Author-email: support@arducam.com
Platform: Windows
Platform: Linux
Classifier: Programming Language :: Python
Classifier: Operating System :: Microsoft :: Windows
Classifier: Operating System :: Unix
